delos/__init__.py
delos/__init__.pyi
delos/client.py
delos/client.pyi
delos/endpoints.py
delos/endpoints.pyi
delos/exceptions.py
delos/exceptions.pyi
delos/models.py
delos/models.pyi
delos/py.typed
delos/releases.py
delos/releases.pyi
delos/settings.py
delos/settings.pyi
delos/utils.py
delos/utils.pyi
delos-0.3.12.dist-info/LICENSE
delos-0.3.12.dist-info/METADATA
delos-0.3.12.dist-info/WHEEL
delos-0.3.12.dist-info/RECORD
