Metadata-Version: 2.3
Name: delos
Version: 0.3.12
Summary: Delos client.
Keywords: AI,LLM,generative
Author: Maria
Author-email: mariaibanez@delosintelligence.fr
Requires-Python: >=3.11,<4.0
Classifier: Programming Language :: Python :: 3
Classifier: Programming Language :: Python :: 3.11
Classifier: Programming Language :: Python :: 3.12
Classifier: Programming Language :: Python :: 3.13
Requires-Dist: aiofiles (>=24.1.0,<25.0.0)
Requires-Dist: aiohttp (>=3.11.13,<4.0.0)
Requires-Dist: fastapi (>=0.115.5,<0.116.0)
Requires-Dist: loguru (>=0.7.2,<0.8.0)
Requires-Dist: pydantic (>=2.10.5,<3.0.0)
Requires-Dist: requests (>=2.32.3,<3.0.0)
